README.md
setup.py
mos/__init__.py
mos/cli/__init__.py
mos/cli/model.py
mos/cli/mosctl.py
mos/cli/user.py
mos_cli.egg-info/PKG-INFO
mos_cli.egg-info/SOURCES.txt
mos_cli.egg-info/dependency_links.txt
mos_cli.egg-info/entry_points.txt
mos_cli.egg-info/not-zip-safe
mos_cli.egg-info/requires.txt
mos_cli.egg-info/top_level.txt