Metadata-Version: 1.1
Name: mos-cli
Version: 0.1.1
Summary: MOS command-line interface
Home-page: https://github.com/Fuinn/mos-cli
Author: Fuinn
Author-email: UNKNOWN
License: BSD 3-Clause License
Platform: UNKNOWN
Classifier: Development Status :: 4 - Beta
Classifier: License :: OSI Approved :: BSD License
Classifier: Operating System :: Microsoft :: Windows
Classifier: Operating System :: MacOS
Classifier: Operating System :: POSIX :: Linux
Classifier: Programming Language :: Python :: 3.6
